pylaprof/__init__.py
pylaprof/scripts/merge.py
pylaprof-0.4.6.dist-info/entry_points.txt
pylaprof-0.4.6.dist-info/LICENSE
pylaprof-0.4.6.dist-info/WHEEL
pylaprof-0.4.6.dist-info/METADATA
pylaprof-0.4.6.dist-info/RECORD
