Metadata-Version: 2.1
Name: pylaprof
Version: 0.4.6
Summary: A Python sampling profiler for AWS Lambda functions (and not only).
Home-page: https://github.com/glumia/pylaprof
License: MIT
Keywords: profiling,flamegraph,lambda,aws,serverless
Author: Giuseppe Lumia
Author-email: gius@glumia.dev
Requires-Python: >=3.7,<4.0
Classifier: Development Status :: 4 - Beta
Classifier: License :: OSI Approved :: MIT License
Classifier: Programming Language :: Python :: 3
Classifier: Programming Language :: Python :: 3.10
Classifier: Programming Language :: Python :: 3.7
Classifier: Programming Language :: Python :: 3.8
Classifier: Programming Language :: Python :: 3.9
Project-URL: Repository, https://github.com/glumia/pylaprof
